<annotation>
	<folder>fish_images</folder>
	<filename>lutjanus_malabaricus_7.jpg</filename>
	<path>D:\bm_img\fish_images\lutjanus_malabaricus_7.jpg</path>
	<source>
		<database>Unknown</database>
	</source>
	<size>
		<width>640</width>
		<height>350</height>
		<depth>3</depth>
	</size>
	<segmented>0</segmented>
	<object>
		<name>fish</name>
		<pose>Unspecified</pose>
		<truncated>0</truncated>
		<difficult>0</difficult>
		<bndbox>
			<xmin>18</xmin>
			<ymin>27</ymin>
			<xmax>614</xmax>
			<ymax>315</ymax>
		</bndbox>
	</object>
</annotation>
